mergecounts/__main__.py
mergecounts/concordance.py
mergecounts/metadata.py
mergecounts/recursive.py
mergecounts/sequential.py
mergecounts/utils/__init__.py
mergecounts/utils/args.py
mergecounts/utils/cache.py
mergecounts/utils/dx.py
mergecounts/utils/errors.py
mergecounts/utils/matrix.py
stjudecloud_merge_counts-1.2.1.dist-info/entry_points.txt
stjudecloud_merge_counts-1.2.1.dist-info/LICENSE.md
stjudecloud_merge_counts-1.2.1.dist-info/WHEEL
stjudecloud_merge_counts-1.2.1.dist-info/METADATA
stjudecloud_merge_counts-1.2.1.dist-info/RECORD
