Metadata-Version: 2.1
Name: stjudecloud-merge-counts
Version: 1.2.1
Summary: Utility for merging RNA-seq expression counts files from St. Jude Cloud.
Home-page: https://github.com/stjudecloud/merge-counts
License: MIT
Keywords: bioinformatics,genomics,htseq
Author: Clay McLeod
Author-email: Clay.McLeod@STJUDE.org
Requires-Python: >=3.8,<4.0
Classifier: Development Status :: 5 - Production/Stable
Classifier: License :: OSI Approved :: MIT License
Classifier: Operating System :: OS Independent
Classifier: Programming Language :: Python :: 3
Classifier: Programming Language :: Python :: 3.8
Classifier: Topic :: Scientific/Engineering :: Bio-Informatics
Requires-Dist: dxpy (==0.310.0)
Requires-Dist: hurry.filesize (>=0.9,<0.10)
Requires-Dist: logzero (>=1.5.0,<2.0.0)
Requires-Dist: pandas (>=1.1.0,<2.0.0)
Requires-Dist: requests (<2.24.0)
Requires-Dist: tables (>=3.6.1,<4.0.0)
Requires-Dist: tqdm (>=4.48.2,<5.0.0)
Project-URL: Repository, https://github.com/stjudecloud/merge-counts
